LICENSE
MANIFEST.in
README.md
requirements.txt
setup.py
muto/__init__.py
muto/admin.py
muto/fields.py
muto/models.py
muto/tests.py
muto/views.py
muto/management/__init__.py
muto/management/commands/__init__.py
muto/management/commands/generateimageversions.py
muto/migrations/0001_initial.py
muto/migrations/__init__.py
muto_client.egg-info/PKG-INFO
muto_client.egg-info/SOURCES.txt
muto_client.egg-info/dependency_links.txt
muto_client.egg-info/not-zip-safe
muto_client.egg-info/requires.txt
muto_client.egg-info/top_level.txt