Metadata-Version: 1.1
Name: muto-client
Version: 0.2.6
Summary: muto is a client/server system for cloud-based image manipulation in Django projects
Home-page: http://github.com/philippbosch/muto-client
Author: Philipp Bosch
Author-email: hello+muto-client@pb.io
License: UNKNOWN
Platform: UNKNOWN
Classifier: Development Status :: 4 - Beta
Classifier: Environment :: Web Environment
Classifier: Intended Audience :: Developers
Classifier: License :: OSI Approved :: MIT License
Classifier: Operating System :: OS Independent
Classifier: Programming Language :: Python
